Workbook

Sheet 使用说明
A1: 请不要直接在表格中编辑，请按下方图示创建副本使用

Sheet 英国
A1: 小店产品定价表 | B1: 备注： 1、O列【各项手续费】包括：欧洲税费VAT20%+小店手续费5%+汇损、提现、货损5%（估算），包裹成本指货物包装/面单成本 2、英镑兑换人民币汇率：8.3 3、英国跨境物流成本价卡：TikTok Shop 英国跨境物流成本价卡
A2: 产品名称 | B2: sku | C2: 手动填写 | D2: 手动填写 | E2: 手动填写 | F2: 手动填写 | G2: 手动填写 | H2: 手动填写 | I2: 勿改 | J2: 勿改 | K2: 手动填写 | L2: 勿改 | M2: 勿改 | N2: 勿改 | O2: 勿改 | P2: 勿改 | Q2: 勿改
B3: 样式 | C3: 进价￥ | D3: 包裹成本￥ | E3: 长（cm） | F3: 宽（cm） | G3: 高（cm） | H3: 实重 g | I3: 体积重 g | J3: 计费重 g | K3: 本地展示价 ￡ | L3: 英国毛利率 | M3: 进价+包裹成本￡ | N3: 跨境物流成本￡ | O3: 各项手续费￡ | P3: 利润￡ | Q3: 利润￥
A4: 例 | B4: 30 bottle | C4: 7 | D4: 1 | E4: 20 | F4: 15 | G4: 5 | H4: 400 | I4: =(E4*F4*G4)/8000*1000 | J4: =MAX(H4,I4) | K4: 20 | L4: =P4/K4*100% | M4: =(C4+D4)/8.3 | N4: =J4/10*0.07 | O4: =K4*0.3 | P4: =K4-O4-M4-N4 | Q4: =P4*8.3
L5: =P5/K5*100% | M5: =(C5+D5)/8.3 | N5: =J5/10*0.07 | O5: =K5*0.3 | P5: =K5-O5-M5-N5 | Q5: =P5*8.3
L6: =P6/K6*100% | M6: =(C6+D6)/8.3 | N6: =J6/10*0.07 | O6: =K6*0.3 | P6: =K6-O6-M6-N6 | Q6: =P6*8.3
L7: =P7/K7*100% | M7: =(C7+D7)/8.3 | N7: =J7/10*0.07 | O7: =K7*0.3 | P7: =K7-O7-M7-N7 | Q7: =P7*8.3
L8: =P8/K8*100% | M8: =(C8+D8)/8.3 | N8: =J8/10*0.07 | O8: =K8*0.3 | P8: =K8-O8-M8-N8 | Q8: =P8*8.3
L9: =P9/K9*100% | M9: =(C9+D9)/8.3 | N9: =J9/10*0.07 | O9: =K9*0.3 | P9: =K9-O9-M9-N9 | Q9: =P9*8.3
L10: =P10/K10*100% | M10: =(C10+D10)/8.3 | N10: =J10/10*0.07 | O10: =K10*0.3 | P10: =K10-O10-M10-N10 | Q10: =P10*8.3
L11: =P11/K11*100% | M11: =(C11+D11)/8.3 | N11: =J11/10*0.07 | O11: =K11*0.3 | P11: =K11-O11-M11-N11 | Q11: =P11*8.3
L12: =P12/K12*100% | M12: =(C12+D12)/8.3 | N12: =J12/10*0.07 | O12: =K12*0.3 | P12: =K12-O12-M12-N12 | Q12: =P12*8.3
L13: =P13/K13*100% | M13: =(C13+D13)/8.3 | N13: =J13/10*0.07 | O13: =K13*0.3 | P13: =K13-O13-M13-N13 | Q13: =P13*8.3
L14: =P14/K14*100% | M14: =(C14+D14)/8.3 | N14: =J14/10*0.07 | O14: =K14*0.3 | P14: =K14-O14-M14-N14 | Q14: =P14*8.3
L15: =P15/K15*100% | M15: =(C15+D15)/8.3 | N15: =J15/10*0.07 | O15: =K15*0.3 | P15: =K15-O15-M15-N15 | Q15: =P15*8.3
L16: =P16/K16*100% | M16: =(C16+D16)/8.3 | N16: =J16/10*0.07 | O16: =K16*0.3 | P16: =K16-O16-M16-N16 | Q16: =P16*8.3

Sheet 马来西亚
A1: 小店产品定价表 | B1: 备注： 1、J列【各项手续费】包括：小店手续费5%+汇损、提现、货损5%（估算），包裹成本指货物包装/面单成本 2、马币兑换人民币汇率：1.5 3、东南亚官方跨境物流成本价卡：TikTok Shop东南亚跨境物流成本价卡
A2: 产品名称 | B2: sku | C2: 手动填写 | D2: 手动填写 | E2: 手动填写 | F2: 手动填写 | G2: 勿改 | H2: 勿改 | I2: 勿改 | J2: 勿改 | K2: 勿改 | L2: 勿改 | M2: 推送优先级 | N2: 是否重复
B3: 样式 | C3: 进价￥ | D3: 包裹成本￥ | E3: 实重 g | F3: 本地展示价 MYR | G3: 毛利率 | H3: 进价+ 包裹成本MYR | I3: 跨境物流成本MYR | J3: 各项手续费MYR | K3: 利润MYR | L3: 利润￥ | M3: 排序 | N3: 历史去重
A4: 例 | B4: 30 bottle | C4: 15 | D4: 1 | E4: 400 | F4: 19 | G4: =K4/F4 | H4: =(C4+D4)/1.5 | I4: =E4/10*0.15 | J4: =F4*0.1 | K4: =F4-J4-H4-I4 | L4: =K4*1.5
A5: 壁挂肥皂盒带沥水 | B5: soap-holder | C5: 2.2 | D5: 0.8 | E5: 120 | F5: 8.9 | G5: =K5/F5 | H5: =(C5+D5)/1.5 | I5: =E5/10*0.15 | J5: =F5*0.1 | K5: =F5-J5-H5-I5 | L5: =K5*1.5 | M5: 4 | N5: =IF(COUNTIF('每日去重表'!$C:$C,B5)>0,"重复","不重复")
A6: 牙刷收纳架 | B6: toothbrush-holder | C6: 1.8 | D6: 0.6 | E6: 90 | F6: 7.9 | G6: =K6/F6 | H6: =(C6+D6)/1.5 | I6: =E6/10*0.15 | J6: =F6*0.1 | K6: =F6-J6-H6-I6 | L6: =K6*1.5 | M6: 2 | N6: =IF(COUNTIF('每日去重表'!$C:$C,B6)>0,"重复","不重复")
A7: 电动牙刷收纳架 | B7: electric-toothbrush-holder | C7: 4.8 | D7: 1 | E7: 180 | F7: 15.9 | G7: =K7/F7 | H7: =(C7+D7)/1.5 | I7: =E7/10*0.15 | J7: =F7*0.1 | K7: =F7-J7-H7-I7 | L7: =K7*1.5 | M7: 11 | N7: =IF(COUNTIF('每日去重表'!$C:$C,B7)>0,"重复","不重复")
A8: 牙膏挤压器 | B8: toothpaste-dispenser | C8: 1.5 | D8: 0.5 | E8: 70 | F8: 6.9 | G8: =K8/F8 | H8: =(C8+D8)/1.5 | I8: =E8/10*0.15 | J8: =F8*0.1 | K8: =F8-J8-H8-I8 | L8: =K8*1.5 | M8: 3 | N8: =IF(COUNTIF('每日去重表'!$C:$C,B8)>0,"重复","不重复")
A9: 卫生纸架带置物台 | B9: toilet-paper-holder-shelf | C9: 6.8 | D9: 1.2 | E9: 350 | F9: 24.9 | G9: =K9/F9 | H9: =(C9+D9)/1.5 | I9: =E9/10*0.15 | J9: =F9*0.1 | K9: =F9-J9-H9-I9 | L9: =K9*1.5 | M9: 15 | N9: =IF(COUNTIF('每日去重表'!$C:$C,B9)>0,"重复","不重复")
A10: 浴室毛巾架 | B10: towel-rack-wall-mounted | C10: 7.2 | D10: 1.5 | E10: 500 | F10: 19.9 | G10: =K10/F10 | H10: =(C10+D10)/1.5 | I10: =E10/10*0.15 | J10: =F10*0.1 | K10: =F10-J10-H10-I10 | L10: =K10*1.5 | M10: 13 | N10: =IF(COUNTIF('每日去重表'!$C:$C,B10)>0,"重复","不重复")
A11: 独立式毛巾架 | B11: towel-rack-stand | C11: 15.5 | D11: 2 | E11: 1200 | F11: 59.9 | G11: =K11/F11 | H11: =(C11+D11)/1.5 | I11: =E11/10*0.15 | J11: =F11*0.1 | K11: =F11-J11-H11-I11 | L11: =K11*1.5 | M11: 20 | N11: =IF(COUNTIF('每日去重表'!$C:$C,B11)>0,"重复","不重复")
A12: 墙面挂钩 | B12: wall-hook | C12: 0.9 | D12: 0.4 | E12: 40 | F12: 5.9 | G12: =K12/F12 | H12: =(C12+D12)/1.5 | I12: =E12/10*0.15 | J12: =F12*0.1 | K12: =F12-J12-H12-I12 | L12: =K12*1.5 | M12: 1 | N12: =IF(COUNTIF('每日去重表'!$C:$C,B12)>0,"重复","不重复")
A13: 马桶刷架 | B13: toilet-brush-holder | C13: 5.4 | D13: 1 | E13: 260 | F13: 18.9 | G13: =K13/F13 | H13: =(C13+D13)/1.5 | I13: =E13/10*0.15 | J13: =F13*0.1 | K13: =F13-J13-H13-I13 | L13: =K13*1.5 | M13: 10 | N13: =IF(COUNTIF('每日去重表'!$C:$C,B13)>0,"重复","不重复")
A14: 鞋架 | B14: shoe-rack | C14: 4.8 | D14: 1.2 | E14: 650 | F14: 12.9 | G14: =K14/F14 | H14: =(C14+D14)/1.5 | I14: =E14/10*0.15 | J14: =F14*0.1 | K14: =F14-J14-H14-I14 | L14: =K14*1.5 | M14: 14 | N14: =IF(COUNTIF('每日去重表'!$C:$C,B14)>0,"重复","不重复")
A15: 鞋柜式鞋架 | B15: shoe-rack-cabinet | C15: 12.5 | D15: 2 | E15: 1800 | F15: 35.9 | G15: =K15/F15 | H15: =(C15+D15)/1.5 | I15: =E15/10*0.15 | J15: =F15*0.1 | K15: =F15-J15-H15-I15 | L15: =K15*1.5 | M15: 18 | N15: =IF(COUNTIF('每日去重表'!$C:$C,B15)>0,"重复","不重复")
A16: 折叠脏衣篮 | B16: foldable-laundry-basket | C16: 5.8 | D16: 1 | E16: 450 | F16: 14.9 | G16: =K16/F16 | H16: =(C16+D16)/1.5 | I16: =E16/10*0.15 | J16: =F16*0.1 | K16: =F16-J16-H16-I16 | L16: =K16*1.5 | M16: 12 | N16: =IF(COUNTIF('每日去重表'!$C:$C,B16)>0,"重复","不重复")
... A24: 床边挂篮 | B24: bedside-hanging-basket | C24: 4.1 | D24: 0.8 | E24: 220 | F24: 14.9 | G24: =K24/F24 | H24: =(C24+D24)/1.5 | I24: =E24/10*0.15 | J24: =F24*0.1 | K24: =F24-J24-H24-I24 | L24: =K24*1.5 | M24: 7 | N24: =IF(COUNTIF('每日去重表'!$C:$C,B24)>0,"重复","不重复")

Sheet 菲律宾
A1: 小店产品定价表 | B1: 备注： 1、J列【各项手续费】包括：小店手续费5%+汇损、提现、货损5%（估算），包裹成本指货物包装/面单成本 2、人民币兑换菲律宾比索汇率：7.8 3、东南亚官方跨境物流成本价卡：TikTok Shop东南亚跨境物流成本价卡
A2: 产品名称 | B2: sku | C2: 手动填写 | D2: 手动填写 | E2: 手动填写 | F2: 手动填写 | G2: 勿改 | H2: 勿改 | I2: 勿改 | J2: 勿改 | K2: 勿改 | L2: 勿改
B3: 样式 | C3: 进价￥ | D3: 包裹成本￥ | E3: 实重 g | F3: 本地展示价 PHP | G3: 毛利率 | H3: 进价+包裹成本PHP | I3: 跨境物流成本PHP | J3: 各项手续费PHP | K3: 利润PHP | L3: 利润￥
A4: 例 | B4: 30 bottle | C4: 15 | D4: 1 | E4: 400 | F4: 400 | G4: =K4/F4*100% | H4: =(C4+D4)*7.8 | I4: =E4/10*4.5 | J4: =F4*0.1 | K4: =F4-J4-H4-I4 | L4: =K4/7.8
A5: 22 | B5: 测试 | C5: 1 | D5: 1 | E5: 50 | F5: 40 | G5: =K5/F5*100% | H5: =(C5+D5)*7.8 | I5: =E5/10*4.5 | J5: =F5*0.1 | K5: =F5-J5-H5-I5 | L5: =K5/7.8
G6: =K6/F6*100% | H6: =(C6+D6)*7.8 | I6: =E6/10*4.5 | J6: =F6*0.1 | K6: =F6-J6-H6-I6 | L6: =K6/7.8
G7: =K7/F7*100% | H7: =(C7+D7)*7.8 | I7: =E7/10*4.5 | J7: =F7*0.1 | K7: =F7-J7-H7-I7 | L7: =K7/7.8
G8: =K8/F8*100% | H8: =(C8+D8)*7.8 | I8: =E8/10*4.5 | J8: =F8*0.1 | K8: =F8-J8-H8-I8 | L8: =K8/7.8
G9: =K9/F9*100% | H9: =(C9+D9)*7.8 | I9: =E9/10*4.5 | J9: =F9*0.1 | K9: =F9-J9-H9-I9 | L9: =K9/7.8
G10: =K10/F10*100% | H10: =(C10+D10)*7.8 | I10: =E10/10*4.5 | J10: =F10*0.1 | K10: =F10-J10-H10-I10 | L10: =K10/7.8
G11: =K11/F11*100% | H11: =(C11+D11)*7.8 | I11: =E11/10*4.5 | J11: =F11*0.1 | K11: =F11-J11-H11-I11 | L11: =K11/7.8
G12: =K12/F12*100% | H12: =(C12+D12)*7.8 | I12: =E12/10*4.5 | J12: =F12*0.1 | K12: =F12-J12-H12-I12 | L12: =K12/7.8
G13: =K13/F13*100% | H13: =(C13+D13)*7.8 | I13: =E13/10*4.5 | J13: =F13*0.1 | K13: =F13-J13-H13-I13 | L13: =K13/7.8
G14: =K14/F14*100% | H14: =(C14+D14)*7.8 | I14: =E14/10*4.5 | J14: =F14*0.1 | K14: =F14-J14-H14-I14 | L14: =K14/7.8
G15: =K15/F15*100% | H15: =(C15+D15)*7.8 | I15: =E15/10*4.5 | J15: =F15*0.1 | K15: =F15-J15-H15-I15 | L15: =K15/7.8
G16: =K16/F16*100% | H16: =(C16+D16)*7.8 | I16: =E16/10*4.5 | J16: =F16*0.1 | K16: =F16-J16-H16-I16 | L16: =K16/7.8
G17: =K17/F17*100% | H17: =(C17+D17)*7.8 | I17: =E17/10*4.5 | J17: =F17*0.1 | K17: =F17-J17-H17-I17 | L17: =K17/7.8
... G20: =K20/F20*100% | H20: =(C20+D20)*7.8 | I20: =E20/10*4.5 | J20: =F20*0.1 | K20: =F20-J20-H20-I20 | L20: =K20/7.8

Sheet 泰国
A1: 小店产品定价表 | B1: 备注： 1、M列【各项手续费】包括：小店手续费5%+汇损、提现、货损合计5%（估算）+泰国交易手续费3%或12泰铢，包裹成本指货物包装/面单成本 2、人民币兑换泰铢汇率：5.1 3、东南亚官方跨境物流成本价卡：TikTok Shop东南亚跨境物流成本价卡
A2: 产品名称 | B2: sku | C2: 手动填写 | D2: 手动填写 | E2: 手动填写 | F2: 手动填写 | G2: 勿改 | H2: 勿改 | I2: 勿改 | J2: 勿改 | K2: 勿改 | L2: 勿改
B3: 样式 | C3: 进价￥ | D3: 包裹成本￥ | E3: 实重 g | F3: 本地展示价 THB | G3: 毛利率 | H3: 包裹成本THB | I3: 跨境物流成本THB | J3: 各项手续费THB | K3: 利润THB | L3: 利润￥
A4: 例 | B4: 30 bottle | C4: 15 | D4: 1 | E4: 400 | F4: 400 | G4: =K4/F4*100% | H4: =(C4+D4)*5.1 | I4: =E4/10*1 | J4: =F4*0.15 | K4: =F4-J4-H4-I4 | L4: =K4/5.1
G5: =K5/F5*100% | H5: =(C5+D5)*5.1 | I5: =E5/10*1 | J5: =F5*0.15 | K5: =F5-J5-H5-I5 | L5: =K5/5.1
G6: =K6/F6*100% | H6: =(C6+D6)*5.1 | I6: =E6/10*1 | J6: =F6*0.15 | K6: =F6-J6-H6-I6 | L6: =K6/5.1
G7: =K7/F7*100% | H7: =(C7+D7)*5.1 | I7: =E7/10*1 | J7: =F7*0.15 | K7: =F7-J7-H7-I7 | L7: =K7/5.1
G8: =K8/F8*100% | H8: =(C8+D8)*5.1 | I8: =E8/10*1 | J8: =F8*0.15 | K8: =F8-J8-H8-I8 | L8: =K8/5.1
G9: =K9/F9*100% | H9: =(C9+D9)*5.1 | I9: =E9/10*1 | J9: =F9*0.15 | K9: =F9-J9-H9-I9 | L9: =K9/5.1
G10: =K10/F10*100% | H10: =(C10+D10)*5.1 | I10: =E10/10*1 | J10: =F10*0.15 | K10: =F10-J10-H10-I10 | L10: =K10/5.1
G11: =K11/F11*100% | H11: =(C11+D11)*5.1 | I11: =E11/10*1 | J11: =F11*0.15 | K11: =F11-J11-H11-I11 | L11: =K11/5.1
G12: =K12/F12*100% | H12: =(C12+D12)*5.1 | I12: =E12/10*1 | J12: =F12*0.15 | K12: =F12-J12-H12-I12 | L12: =K12/5.1
G13: =K13/F13*100% | H13: =(C13+D13)*5.1 | I13: =E13/10*1 | J13: =F13*0.15 | K13: =F13-J13-H13-I13 | L13: =K13/5.1
G14: =K14/F14*100% | H14: =(C14+D14)*5.1 | I14: =E14/10*1 | J14: =F14*0.15 | K14: =F14-J14-H14-I14 | L14: =K14/5.1
G15: =K15/F15*100% | H15: =(C15+D15)*5.1 | I15: =E15/10*1 | J15: =F15*0.15 | K15: =F15-J15-H15-I15 | L15: =K15/5.1
G16: =K16/F16*100% | H16: =(C16+D16)*5.1 | I16: =E16/10*1 | J16: =F16*0.15 | K16: =F16-J16-H16-I16 | L16: =K16/5.1
... G20: =K20/F20*100% | H20: =(C20+D20)*5.1 | I20: =E20/10*1 | J20: =F20*0.15 | K20: =F20-J20-H20-I20 | L20: =K20/5.1

Sheet 越南
A1: 小店产品定价表 | B1: 备注： 1、J列【各项手续费】包括：小店手续费5%+汇损、提现、货损5%（估算），包裹成本指货物包装/面单成本 2、人民币对越南盾汇率：3464.7 3、东南亚官方跨境物流成本价卡：TikTok Shop东南亚跨境物流成本价卡
A2: 产品名称 | B2: sku | C2: 手动填写 | D2: 手动填写 | E2: 手动填写 | F2: 手动填写 | G2: 勿改 | H2: 勿改 | I2: 勿改 | J2: 勿改 | K2: 勿改 | L2: 勿改
B3: 样式 | C3: 进价￥ | D3: 包裹成本￥ | E3: 实重 g | F3: 本地展示价 VND | G3: 毛利率 | H3: 进价+包裹成本VND | I3: 跨境物流成本VND | J3: 各项手续费VND | K3: 利润VND | L3: 利润￥
A4: 例 | B4: 30 bottle | C4: 15 | D4: 1 | E4: 400 | F4: 1200000 | G4: =K4/F4*100% | H4: =(C4+D4)*3464.7 | I4: =E4/10*900 | J4: =F4*0.1 | K4: =F4-J4-H4-I4 | L4: =K4/3464.7
G5: =K5/F5*100% | H5: =(C5+D5)*3464.7 | I5: =E5/10*900 | J5: =F5*0.1 | K5: =F5-J5-H5-I5 | L5: =K5/3464.7
G6: =K6/F6*100% | H6: =(C6+D6)*3464.7 | I6: =E6/10*900 | J6: =F6*0.1 | K6: =F6-J6-H6-I6 | L6: =K6/3464.7
G7: =K7/F7*100% | H7: =(C7+D7)*3464.7 | I7: =E7/10*900 | J7: =F7*0.1 | K7: =F7-J7-H7-I7 | L7: =K7/3464.7
G8: =K8/F8*100% | H8: =(C8+D8)*3464.7 | I8: =E8/10*900 | J8: =F8*0.1 | K8: =F8-J8-H8-I8 | L8: =K8/3464.7
G9: =K9/F9*100% | H9: =(C9+D9)*3464.7 | I9: =E9/10*900 | J9: =F9*0.1 | K9: =F9-J9-H9-I9 | L9: =K9/3464.7
G10: =K10/F10*100% | H10: =(C10+D10)*3464.7 | I10: =E10/10*900 | J10: =F10*0.1 | K10: =F10-J10-H10-I10 | L10: =K10/3464.7
G11: =K11/F11*100% | H11: =(C11+D11)*3464.7 | I11: =E11/10*900 | J11: =F11*0.1 | K11: =F11-J11-H11-I11 | L11: =K11/3464.7
G12: =K12/F12*100% | H12: =(C12+D12)*3464.7 | I12: =E12/10*900 | J12: =F12*0.1 | K12: =F12-J12-H12-I12 | L12: =K12/3464.7
G13: =K13/F13*100% | H13: =(C13+D13)*3464.7 | I13: =E13/10*900 | J13: =F13*0.1 | K13: =F13-J13-H13-I13 | L13: =K13/3464.7
G14: =K14/F14*100% | H14: =(C14+D14)*3464.7 | I14: =E14/10*900 | J14: =F14*0.1 | K14: =F14-J14-H14-I14 | L14: =K14/3464.7
G15: =K15/F15*100% | H15: =(C15+D15)*3464.7 | I15: =E15/10*900 | J15: =F15*0.1 | K15: =F15-J15-H15-I15 | L15: =K15/3464.7
G16: =K16/F16*100% | H16: =(C16+D16)*3464.7 | I16: =E16/10*900 | J16: =F16*0.1 | K16: =F16-J16-H16-I16 | L16: =K16/3464.7

Sheet 新加坡
A1: 小店产品定价表 | B1: 备注： 1、O列【各项手续费】包括：小店手续费5%+汇损、提现、货损5%（估算），包裹成本指货物包装/面单成本 2、新加坡币兑人民币汇率：4.8 3、东南亚官方跨境物流成本价卡：TikTok Shop东南亚跨境物流成本价卡
A2: 产品名称 | B2: sku | C2: 手动填写 | D2: 手动填写 | E2: 手动填写 | F2: 手动填写 | G2: 勿改 | H2: 勿改 | I2: 勿改 | J2: 勿改 | K2: 勿改 | L2: 勿改
B3: 样式 | C3: 进价￥ | D3: 包裹成本￥ | E3: 实重 g | F3: 本地展示价 SGD | G3: 毛利率 | H3: 进价+包裹成本SGD | I3: 跨境物流成本SGD | J3: 各项手续费SGD | K3: 利润SGD | L3: 利润￥
A4: 例 | B4: 30 bottle | C4: 15 | D4: 1 | E4: 400 | F4: 29 | G4: =K4/F4*100% | H4: =(C4+D4)/4.8 | I4: =(E4-50)/10*0.15+0.7 | J4: =F4*0.1 | K4: =F4-J4-H4-I4 | L4: =K4*4.8
G5: =K5/F5*100% | H5: =(C5+D5)/4.8 | I5: =(E5-50)/10*0.15+0.7 | J5: =F5*0.1 | K5: =F5-J5-H5-I5 | L5: =K5*4.8
G6: =K6/F6*100% | H6: =(C6+D6)/4.8 | I6: =(E6-50)/10*0.15+0.7 | J6: =F6*0.1 | K6: =F6-J6-H6-I6 | L6: =K6*4.8
G7: =K7/F7*100% | H7: =(C7+D7)/4.8 | I7: =(E7-50)/10*0.15+0.7 | J7: =F7*0.1 | K7: =F7-J7-H7-I7 | L7: =K7*4.8
G8: =K8/F8*100% | H8: =(C8+D8)/4.8 | I8: =(E8-50)/10*0.15+0.7 | J8: =F8*0.1 | K8: =F8-J8-H8-I8 | L8: =K8*4.8
G9: =K9/F9*100% | H9: =(C9+D9)/4.8 | I9: =(E9-50)/10*0.15+0.7 | J9: =F9*0.1 | K9: =F9-J9-H9-I9 | L9: =K9*4.8
G10: =K10/F10*100% | H10: =(C10+D10)/4.8 | I10: =(E10-50)/10*0.15+0.7 | J10: =F10*0.1 | K10: =F10-J10-H10-I10 | L10: =K10*4.8
G11: =K11/F11*100% | H11: =(C11+D11)/4.8 | I11: =(E11-50)/10*0.15+0.7 | J11: =F11*0.1 | K11: =F11-J11-H11-I11 | L11: =K11*4.8
G12: =K12/F12*100% | H12: =(C12+D12)/4.8 | I12: =(E12-50)/10*0.15+0.7 | J12: =F12*0.1 | K12: =F12-J12-H12-I12 | L12: =K12*4.8
G13: =K13/F13*100% | H13: =(C13+D13)/4.8 | I13: =(E13-50)/10*0.15+0.7 | J13: =F13*0.1 | K13: =F13-J13-H13-I13 | L13: =K13*4.8
G14: =K14/F14*100% | H14: =(C14+D14)/4.8 | I14: =(E14-50)/10*0.15+0.7 | J14: =F14*0.1 | K14: =F14-J14-H14-I14 | L14: =K14*4.8
G15: =K15/F15*100% | H15: =(C15+D15)/4.8 | I15: =(E15-50)/10*0.15+0.7 | J15: =F15*0.1 | K15: =F15-J15-H15-I15 | L15: =K15*4.8
G16: =K16/F16*100% | H16: =(C16+D16)/4.8 | I16: =(E16-50)/10*0.15+0.7 | J16: =F16*0.1 | K16: =F16-J16-H16-I16 | L16: =K16*4.8
... G20: =K20/F20*100% | H20: =(C20+D20)/4.8 | I20: =(E20-50)/10*0.15+0.7 | J20: =F20*0.1 | K20: =F20-J20-H20-I20 | L20: =K20*4.8

Sheet 美国
A1: 独立站产品定价表 | B1: 备注： 1、M和N列【挂号费和运费】需要根据物流公司渠道报价填写 2、O列【各项手续费】包括：shopify手续费0.5%/1%/2%（根据所选套餐）、paypal手续费5%（估算）、第三方提现平台手续费1%（估算）、汇损
A2: 产品名称 | B2: sku | C2: 手动填写 | D2: 手动填写 | E2: 手动填写 | F2: 手动填写 | G2: 手动填写 | H2: 手动填写 | I2: 勿改 | J2: 勿改 | K2: 手动填写 | L2: 勿改 | M2: 手动填写 | O2: 勿改 | P2: 勿改 | Q2: 勿改 | R2: 勿改 | S2: 勿改
B3: 样式 | C3: 进价￥ | D3: 包材￥ | E3: 长（cm） | F3: 宽（cm） | G3: 高（cm） | H3: 实重 g | I3: 体积重 g | J3: 计费重 g | K3: 独立站售价$ | L3: 独立站毛利率 | M3: 挂号费￥ | N3: 运费（RMB/KG） | O3: 物流费用 ￥ | P3: 总成本$ | Q3: 各项手续费$ | R3: 利润$ | S3: 利润￥
A4: 例 | B4: 30 bottle | C4: 15 | D4: 1 | E4: 20 | F4: 15 | G4: 5 | H4: 400 | I4: =(E4*F4*G4)/8000*1000 | J4: =MAX(H4,I4) | K4: 19 | L4: =R4/K4*100% | M4: 20 | N4: 120 | O4: =J4/1000*N4+M4 | P4: =(O4+C4+D4)/6.3 | Q4: =K4*0.1 | R4: =K4-Q4-P4 | S4: =R4*6.3

Sheet 每日去重表
A1: 日期 | B1: 产品名 | C1: sku | D1: 是否已推送 | E1: 推送渠道 | F1: 备注
A2: 2026-05-27 | B2: 免打孔拖把挂架 | C2: mop-holder-wall-mounted | D2: 已推送 | E2: TikTok | F2: 历史去重样本
A3: 2026-05-27 | B3: 缝隙清洁刷 | C3: gap-cleaning-brush | D3: 已推送 | E3: TikTok | F3: 历史去重样本
A4: 2026-05-27 | B4: 浴室免打孔转角架 | C4: bathroom-corner-shelf | D4: 已推送 | E4: TikTok | F4: 历史去重样本
A5: 2026-05-27 | B5: 抽屉分隔收纳盒 | C5: drawer-organizer-box | D5: 已推送 | E5: TikTok | F5: 历史去重样本
A6: 2026-05-27 | B6: 壁挂肥皂盒带沥水 | C6: wall-mounted-soap-holder | D6: 已推送 | E6: TikTok | F6: 历史去重样本
A7: 2026-05-27 | B7: 桌面多格收纳盒 | C7: desktop-storage-box | D7: 已推送 | E7: TikTok | F7: 历史去重样本
A8: 2026-05-27 | B8: 免打孔卷纸架带置物台 | C8: toilet-paper-holder-shelf | D8: 已推送 | E8: TikTok | F8: 历史去重样本
A9: 2026-05-27 | B9: 衣柜挂袋收纳器 | C9: wardrobe-organizer | D9: 已推送 | E9: TikTok | F9: 历史去重样本
A10: 2026-05-27 | B10: 床底收纳袋 | C10: under-bed-storage-bag | D10: 已推送 | E10: TikTok | F10: 历史去重样本
A11: 2026-05-27 | B11: 滚筒粘毛器 | C11: lint-roller | D11: 已推送 | E11: TikTok | F11: 历史去重样本
